kkbuild.py
kkbuild-0.3.2.dist-info/LICENSE
kkbuild-0.3.2.dist-info/METADATA
kkbuild-0.3.2.dist-info/WHEEL
kkbuild-0.3.2.dist-info/RECORD
