Metadata-Version: 2.1
Name: kkbuild
Version: 0.3.2
Summary: Building blocks for creating various build pipelines
Home-page: https://github.com/kakyoism/kkbuild/
License: MIT
Keywords: utility,devops
Author: Beinan Li
Author-email: li.beinan@gmail.com
Maintainer: Beinan Li
Maintainer-email: li.beinan@gmail.com
Requires-Python: >=3.11,<4.0
Classifier: License :: OSI Approved :: MIT License
Classifier: Programming Language :: Python :: 3
Classifier: Programming Language :: Python :: 3.11
Requires-Dist: kkpyutil
Project-URL: Documentation, https://github.com/kakyoism/kkbuild/README.md
Project-URL: Repository, https://github.com/kakyoism/kkbuild/
Project-URL: issues, https://github.com/kakyoism/kkbuild/issues
